AC's/AC1_Theldo/Guias/Guia_09/clock.v
// ------------------------- 
// Clock.v
// Clock Generator
// Nome: Caio Faria Diniz 
// Matricula: 793605
// ------------------------- 

module clock ( output clk ); 
    reg clk;
    
    initial begin : start
    clk = 1'b0; 
    end // start

    always begin : clock 
        #12 clk = ~clk; 
    end // clock
endmodule // clock ( )

AC's/AC1_Theldo/Guias/Guia_09/Guia_0905.v
// ------------------------- 
// Guia_0905.v
// Test Clock Generator (6) 
// Nome: Caio Faria Diniz 
// Matricula: 793605
// ------------------------- 

`include "clock.v" 

module pulse1 ( signal, clock ); 
    input  clock; 
    output signal; 
    reg    signal; 
    
    always @ ( posedge clock ) 
    begin : pulse
        #2  signal = 1'b1;  
        #2  signal = 1'b0;  
        #2  signal = 1'b1;
        #2  signal = 1'b0;
        #2  signal = 1'b1;
        #2  signal = 1'b0;
        #2  signal = 1'b1;
        #2  signal = 1'b0;
    end // end pulse
endmodule // pulse1 ( )

module pulse2 ( signal, clock ); 
    input  clock; 
    output signal; 
    reg    signal; 
    
    always @ ( posedge clock ) 
    begin : pulse
        signal = 1'b1;  
        #4  signal = 1'b0;  
    end // end pulse
endmodule // pulse2 ( )

module Guia_0905; 
    wire  clock; 
    clock clk ( clock ); 
    
    wire  p1, p2; 
    pulse1 pls1 ( p1, clock ); 
    pulse2 pls2 ( p2, clock ); 
    
    initial begin : main 
        $dumpfile ( "Guia_0905.vcd" ); 
        $dumpvars ( 1, clock, p1, p2 ); 
        
        #480 $finish; 
    end // main
endmodule // Guia_0905 ( )

AC's/AC1_Theldo/Guias/Guia_09/Guia_0905.vcd
$date
	Sat Sep 28 10:02:05 2024
$end
$version
	Icarus Verilog
$end
$timescale
	1s
$end
$scope module Guia_0905 $end
$var wire 1 ! clock $end
$upscope $end
$scope module Guia_0905 $end
$var wire 1 " p1 $end
$upscope $end
$scope module Guia_0905 $end
$var wire 1 # p2 $end
$upscope $end
$enddefinitions $end
$comment Show the parameter values. $end
$dumpall
$end
#0
$dumpvars
x#
x"
0!
$end
#12
1#
1!
#14
1"
#16
0"
0#
#18
1"
#20
0"
#22
1"
#24
0"
0!
#26
1"
#28
0"
#36
1#
1!
#38
1"
#40
0"
0#
#42
1"
#44
0"
#46
1"
#48
0"
0!
#50
1"
#52
0"
#60
1#
1!
#62
1"
#64
0"
0#
#66
1"
#68
0"
#70
1"
#72
0"
0!
#74
1"
#76
0"
#84
1#
1!
#86
1"
#88
0"
0#
#90
1"
#92
0"
#94
1"
#96
0"
0!
#98
1"
#100
0"
#108
1#
1!
#110
1"
#112
0"
0#
#114
1"
#116
0"
#118
1"
#120
0"
0!
#122
1"
#124
0"
#132
1#
1!
#134
1"
#136
0"
0#
#138
1"
#140
0"
#142
1"
#144
0"
0!
#146
1"
#148
0"
#156
1#
1!
#158
1"
#160
0"
0#
#162
1"
#164
0"
#166
1"
#168
0"
0!
#170
1"
#172
0"
#180
1#
1!
#182
1"
#184
0"
0#
#186
1"
#188
0"
#190
1"
#192
0"
0!
#194
1"
#196
0"
#204
1#
1!
#206
1"
#208
0"
0#
#210
1"
#212
0"
#214
1"
#216
0"
0!
#218
1"
#220
0"
#228
1#
1!
#230
1"
#232
0"
0#
#234
1"
#236
0"
#238
1"
#240
0"
0!
#242
1"
#244
0"
#252
1#
1!
#254
1"
#256
0"
0#
#258
1"
#260
0"
#262
1"
#264
0"
0!
#266
1"
#268
0"
#276
1#
1!
#278
1"
#280
0"
0#
#282
1"
#284
0"
#286
1"
#288
0"
0!
#290
1"
#292
0"
#300
1#
1!
#302
1"
#304
0"
0#
#306
1"
#308
0"
#310
1"
#312
0"
0!
#314
1"
#316
0"
#324
1#
1!
#326
1"
#328
0"
0#
#330
1"
#332
0"
#334
1"
#336
0"
0!
#338
1"
#340
0"
#348
1#
1!
#350
1"
#352
0"
0#
#354
1"
#356
0"
#358
1"
#360
0"
0!
#362
1"
#364
0"
#372
1#
1!
#374
1"
#376
0"
0#
#378
1"
#380
0"
#382
1"
#384
0"
0!
#386
1"
#388
0"
#396
1#
1!
#398
1"
#400
0"
0#
#402
1"
#404
0"
#406
1"
#408
0"
0!
#410
1"
#412
0"
#420
1#
1!
#422
1"
#424
0"
0#
#426
1"
#428
0"
#430
1"
#432
0"
0!
#434
1"
#436
0"
#444
1#
1!
#446
1"
#448
0"
0#
#450
1"
#452
0"
#454
1"
#456
0"
0!
#458
1"
#460
0"
#468
1#
1!
#470
1"
#472
0"
0#
#474
1"
#476
0"
#478
1"
#480
0"
0!
