AC's/AC1_Theldo/Guias/Guia_09/clock.v
// ------------------------- 
// Clock.v
// Clock Generator
// Nome: Caio Faria Diniz 
// Matricula: 793605
// ------------------------- 

module clock ( output clk ); 
    reg clk;
    
    initial begin : start
    clk = 1'b0; 
    end // start

    always begin : clock 
        #12 clk = ~clk; 
    end // clock
endmodule // clock ( )

AC's/AC1_Theldo/Guias/Guia_09/Guia_0903.v
// ------------------------- 
// Guia_0903.v
// Test Clock Generator (4) 
// Nome: Caio Faria Diniz 
// Matricula: 793605
// ------------------------- 
`include "clock.v" 

module pulse ( signal, clock ); 
    input  clock; 
    output signal; 
    reg    signal; 
    
    always @ ( posedge clock ) 
    begin : pulse
        signal = 1'b1;
        #32 signal = 1'b0; 
        #64 signal = 1'b1;
        #32 signal = 1'b0;  
    end // end pulse
endmodule // pulse ( )

module Guia_0903; 
    wire  clock; 
    clock clk ( clock ); 
    
    wire  p1; 
    pulse pls1 ( p1, clock ); 
    
    initial begin : main 
        $dumpfile ( "Guia_0903.vcd" ); 
        $dumpvars ( 1, clock, p1 ); 
        
        #480 $finish; 
    end // main
endmodule // Guia_0903 ( )

AC's/AC1_Theldo/Guias/Guia_09/Guia_0903.vcd
$date
	Sat Sep 28 10:01:29 2024
$end
$version
	Icarus Verilog
$end
$timescale
	1s
$end
$scope module Guia_0903 $end
$var wire 1 ! clock $end
$upscope $end
$scope module Guia_0903 $end
$var wire 1 " p1 $end
$upscope $end
$enddefinitions $end
$comment Show the parameter values. $end
$dumpall
$end
#0
$dumpvars
x"
0!
$end
#12
1"
1!
#24
0!
#36
1!
0"
#48
0!
#60
1!
#72
0!
#84
1!
1"
#96
0!
#108
1!
1"
#120
0!
#132
1!
0"
#144
0!
#156
1!
#168
0!
#180
1!
1"
#192
0!
#204
1!
1"
#216
0!
#228
1!
0"
#240
0!
#252
1!
#264
0!
#276
1!
1"
#288
0!
#300
1!
1"
#312
0!
#324
1!
0"
#336
0!
#348
1!
#360
0!
#372
1!
1"
#384
0!
#396
1!
1"
#408
0!
#420
1!
0"
#432
0!
#444
1!
#456
0!
#468
1!
1"
